spotgui/ctk/CTk.py
spotgui/ctk/HyperparameterFrame.py
spotgui/ctk/SelectOptions.py
spotgui/ctk/images/spotlogo.png
spotgui/eda/pairplot.py
spotgui/tuner/spotRun.py
spotgui/tuner/images/spotlogo.png
spotgui-1.0.4.dist-info/LICENSE.txt
spotgui-1.0.4.dist-info/METADATA
spotgui-1.0.4.dist-info/WHEEL
spotgui-1.0.4.dist-info/top_level.txt
spotgui-1.0.4.dist-info/RECORD
