Metadata-Version: 2.1
Name: spotgui
Version: 1.0.4
Summary: spotgui - GUI for the Sequential Parameter Optimization in Python
Author-email: "T. Bartz-Beielstein" <tbb@bartzundbartz.de>
License: AGPL-3.0-or-later
Project-URL: Homepage, https://www.spotseven.de
Project-URL: Issues, https://github.com/sequential-parameter-optimization/spotgui/issues
Project-URL: Repository, https://github.com/sequential-parameter-optimization/spotgui
Classifier: Programming Language :: Python :: 3.10
Classifier: Programming Language :: Python :: 3.11
Classifier: Programming Language :: Python :: 3.12
Classifier: License :: OSI Approved :: GNU Affero General Public License v3 or later (AGPLv3+)
Classifier: Operating System :: OS Independent
Requires-Python: >=3.10
License-File: LICENSE.txt
Requires-Dist: captum
Requires-Dist: customtkinter
Requires-Dist: lightning >=2.4.0
Requires-Dist: graphviz
Requires-Dist: matplotlib
Requires-Dist: mkdocs
Requires-Dist: mkdocs-material
Requires-Dist: mkdocstrings-python
Requires-Dist: mkdocs-exclude
Requires-Dist: mkdocs-gen-files
Requires-Dist: mkdocs-literate-nav
Requires-Dist: mkdocs-section-index
Requires-Dist: numpy
Requires-Dist: nbformat
Requires-Dist: pandas
Requires-Dist: plotly
Requires-Dist: PyQt6
Requires-Dist: python-markdown-math
Requires-Dist: pytorch-lightning >=1.4
Requires-Dist: river >=0.21.0
Requires-Dist: scikit-learn
Requires-Dist: scipy
Requires-Dist: spotpython >=0.15.6
Requires-Dist: spotriver >=0.4.3
Requires-Dist: seaborn
Requires-Dist: tabulate
Requires-Dist: tensorboard
Requires-Dist: torch
Requires-Dist: torch-tb-profiler
Requires-Dist: torchmetrics
Requires-Dist: torchvision
